tenuo-0.1.0a13.dist-info/METADATA
tenuo-0.1.0a13.dist-info/WHEEL
tenuo-0.1.0a13.dist-info/entry_points.txt
tenuo/__init__.py
tenuo/audit.py
tenuo/bound_warrant.py
tenuo/builder.py
tenuo/cli.py
tenuo/config.py
tenuo/constraints.py
tenuo/decorators.py
tenuo/diagnostics.py
tenuo/exceptions.py
tenuo/explain.py
tenuo/fastapi.py
tenuo/keys.py
tenuo/langchain.py
tenuo/langgraph.py
tenuo/mcp/__init__.py
tenuo/mcp/client.py
tenuo/mcp/langchain.py
tenuo/schemas.py
tenuo/scoped.py
tenuo/templates.py
tenuo/testing.py
tenuo/validation.py
tenuo/warrant_ext.py
tenuo_core/__init__.py
tenuo_core/tenuo_core.pyd
tenuo-0.1.0a13.dist-info/RECORD
