Metadata-Version: 2.4
Name: tenuo
Version: 0.1.0a13
Classifier: Development Status :: 3 - Alpha
Classifier: Intended Audience :: Developers
Classifier: License :: OSI Approved :: MIT License
Classifier: License :: OSI Approved :: Apache Software License
Classifier: Programming Language :: Python :: 3
Classifier: Programming Language :: Python :: 3.9
Classifier: Programming Language :: Python :: 3.10
Classifier: Programming Language :: Python :: 3.11
Classifier: Programming Language :: Python :: 3.12
Classifier: Programming Language :: Rust
Classifier: Topic :: Security
Classifier: Topic :: Software Development :: Libraries
Requires-Dist: pyyaml>=6.0
Requires-Dist: pydantic>=2.0
Requires-Dist: langchain-core>=0.2 ; extra == 'langchain'
Requires-Dist: langgraph>=0.0.10 ; extra == 'langgraph'
Requires-Dist: tenuo[langchain] ; extra == 'langgraph'
Requires-Dist: mcp>=1.0.0 ; python_full_version >= '3.10' and extra == 'mcp'
Requires-Dist: rich>=10.0.0 ; extra == 'cli'
Requires-Dist: maturin>=1.0 ; extra == 'dev'
Requires-Dist: pytest>=7.0 ; extra == 'dev'
Requires-Dist: pytest-asyncio ; extra == 'dev'
Requires-Dist: ruff>=0.1.0 ; extra == 'dev'
Requires-Dist: mypy>=1.0 ; extra == 'dev'
Requires-Dist: types-pyyaml ; extra == 'dev'
Requires-Dist: types-requests ; extra == 'dev'
Requires-Dist: fastapi ; extra == 'dev'
Requires-Dist: uvicorn ; extra == 'dev'
Requires-Dist: langchain ; extra == 'dev'
Requires-Dist: langchain-openai ; extra == 'dev'
Requires-Dist: tenuo[langchain,langgraph] ; extra == 'dev'
Provides-Extra: langchain
Provides-Extra: langgraph
Provides-Extra: mcp
Provides-Extra: cli
Provides-Extra: dev
Summary: Capability tokens for AI agents - Python SDK
Keywords: authorization,capabilities,agents,security,warrants,mcp
Author: Tenuo Contributors
License: MIT OR Apache-2.0
Requires-Python: >=3.9
Project-URL: Homepage, https://tenuo.dev
Project-URL: Documentation, https://tenuo.dev/quickstart
Project-URL: Repository, https://github.com/tenuo-ai/tenuo
Project-URL: Issues, https://github.com/tenuo-ai/tenuo/issues
